yc_django_basic_chat/__init__.py
yc_django_basic_chat/admin.py
yc_django_basic_chat/apps.py
yc_django_basic_chat/helper.py
yc_django_basic_chat/models.py
yc_django_basic_chat/serializers.py
yc_django_basic_chat/settings.py
yc_django_basic_chat/tests.py
yc_django_basic_chat/urls.py
yc_django_basic_chat/views.py
yc_django_basic_chat/api/__init__.py
yc_django_basic_chat/api/az_models_curd.py
yc_django_basic_chat/api/conversation_curd.py
yc_django_basic_chat/api/message_curd.py
yc_django_basic_chat/api/qa.py
yc_django_basic_chat/api/qa_stream.py
yc_django_basic_chat/migrations/__init__.py
yc_django_basic_chat-0.0.1.dist-info/LICENSE
yc_django_basic_chat-0.0.1.dist-info/METADATA
yc_django_basic_chat-0.0.1.dist-info/WHEEL
yc_django_basic_chat-0.0.1.dist-info/top_level.txt
yc_django_basic_chat-0.0.1.dist-info/RECORD
