Metadata-Version: 2.1
Name: yc_django_basic_chat
Version: 0.0.1
Summary: Django工具集开发
Author: LiuFei
Author-email: liufei-love@foxmail.com
License: MIT
Classifier: License :: OSI Approved :: MIT License
Classifier: Programming Language :: Python :: 3.12
License-File: LICENSE
Requires-Dist: yc-django-utils >=0.0.5
Requires-Dist: langchain >=0.2.10
Requires-Dist: langchain-openai >=0.1.17
